shoutyorm.py
django_shouty_orm-0.1.1.dist-info/LICENSE
django_shouty_orm-0.1.1.dist-info/METADATA
django_shouty_orm-0.1.1.dist-info/WHEEL
django_shouty_orm-0.1.1.dist-info/top_level.txt
django_shouty_orm-0.1.1.dist-info/RECORD
