Metadata-Version: 2.1
Name: django-shouty-orm
Version: 0.1.1
Summary: Applies a monkeypatch which forces Django's ORM to error far more loudly in certain cases
Home-page: https://github.com/kezabelle/django-shouty-orm
Author: Keryn Knight
Author-email: django-shouty-orm@kerynknight.com
Maintainer: Keryn Knight
Maintainer-email: django-shouty-orm@kerynknight.com
License: BSD License
Keywords: django orm sql exception
Platform: UNKNOWN
Classifier: Development Status :: 3 - Alpha
Classifier: Intended Audience :: Developers
Classifier: License :: OSI Approved :: BSD License
Classifier: Natural Language :: English
Classifier: Programming Language :: Python
Classifier: Programming Language :: Python :: 2
Classifier: Programming Language :: Python :: 2.7
Classifier: Programming Language :: Python :: 3
Classifier: Programming Language :: Python :: 3.5
Classifier: Programming Language :: Python :: 3.6
Classifier: Framework :: Django
Requires-Dist: Django (>=2.2)
Requires-Dist: wrapt (>=1.11)
